{
  "name": "KoquiFI Lottery",
  "version": "1",
  "iconUrl": "https://cdn-icons-png.flaticon.com/512/2583/2583344.png",
  "homeUrl": "https://koquifi-farcaster-frame-815l.vercel.app/miniapp.html",
  "imageUrl": "https://images.unsplash.com/photo-1606092195730-5d7b9af1efc5?w=1200&h=630&fit=crop",
  "buttonTitle": "Jugar Lotería",
  "splashImageUrl": "https://images.unsplash.com/photo-1606092195730-5d7b9af1efc5?w=1200&h=630&fit=crop",
  "splashBackgroundColor": "#FF6B35",
  "webhookUrl": "https://koquifi-farcaster-frame-815l.vercel.app/api/webhook",
  "subtitle": "Lotería KOKI Base Network",
  "description": "Lotería semanal con tokens KOKI en Base Network. Compra tickets, elige números y gana premios increíbles cada lunes. Sistema 100% descentralizado.",
  "primaryCategory": "finance",
  "screenshotUrls": ["https://images.unsplash.com/photo-1606092195730-5d7b9af1efc5?w=1200&h=630&fit=crop"],
  "heroImageUrl": "https://images.unsplash.com/photo-1606092195730-5d7b9af1efc5?w=1200&h=630&fit=crop",
  "tags": ["lottery", "defi", "base", "koki", "tokens"],
  "tagline": "Gana Premios Increíbles",
  "ogTitle": "KoquiFI Lottery",
  "ogDescription": "Compra tickets, elige números y gana premios increíbles cada lunes en Base Network.",
  "ogImageUrl": "https://images.unsplash.com/photo-1606092195730-5d7b9af1efc5?w=1200&h=630&fit=crop",
  "castShareUrl": "https://warpcast.com/~/compose?text=🎰%20Participa%20en%20KoquiFI%20Lottery%20-%20Lotería%20semanal%20con%20tokens%20KOKI%20en%20Base%20Network%20https://koquifi-farcaster-frame-815l.vercel.app"
}
